dabarqus/__init__.py
dabarqus/client.py
dabarqus/install_service.py
dabarqus_sdk/__init__.py
dabarqus_sdk/client.py
dabarqus-1.1.2.dist-info/LICENSE
dabarqus-1.1.2.dist-info/METADATA
dabarqus-1.1.2.dist-info/WHEEL
dabarqus-1.1.2.dist-info/entry_points.txt
dabarqus-1.1.2.dist-info/top_level.txt
dabarqus-1.1.2.dist-info/RECORD
