Metadata-Version: 2.1
Name: dabarqus
Version: 1.1.2
Summary: A Python SDK for interacting with the Dabarqus REST API
Home-page: https://github.com/electricpipelines/dabarqus-python
Author: Xavier Gray
Author-email: xay@electricpipelines.com
Classifier: Development Status :: 4 - Beta
Classifier: Intended Audience :: Developers
Classifier: License :: OSI Approved :: MIT License
Classifier: Operating System :: OS Independent
Classifier: Programming Language :: Python :: 3
Classifier: Programming Language :: Python :: 3.7
Classifier: Programming Language :: Python :: 3.8
Classifier: Programming Language :: Python :: 3.9
Classifier: Programming Language :: Python :: 3.10
Requires-Python: >=3.7
License-File: LICENSE
Requires-Dist: requests<3.0.0,>=2.25.0
Requires-Dist: tqdm<5.0.0,>=4.0.0
Requires-Dist: py7zr<1.0.0,>=0.11.0
Provides-Extra: dev
Requires-Dist: pytest>=6.0.0; extra == "dev"
Requires-Dist: pytest-cov>=2.10.0; extra == "dev"
